{"cameraMode":{"drawMode":0,"name":"Shaded","section":"Shading Mode"},"sceneLighting":true,"audioPlay":false,"sceneViewState":{"m_AlwaysRefresh":false,"showFog":true,"showSkybox":true,"showFlares":true,"showImageEffects":true,"showParticleSystems":true,"showVisualEffectGraphs":true,"m_FxEnabled":true},"in2DMode":false,"pivot":{"x":-0.2745501399040222,"y":-18.005952835083009,"z":33.83153533935547},"rotation":{"x":-0.25109416246414187,"y":-0.0008739700424484909,"z":0.0002264187642140314,"w":-0.9679650068283081},"size":22.052949905395509,"orthographic":false}